{"hash":"2c238d72ba829313ec8f62c1dd3d56a5d46f0cadadca932fae9d343f57a6e82a","n":298,"dur":64.418000896,"words":[{"w":"Một","s":0},{"w":"khi","s":0.12},{"w":"đã","s":0.24},{"w":"xác","s":0.44},{"w":"định","s":0.72},{"w":"xong","s":0.86},{"w":"logic","s":1.12},{"w":"cho","s":1.44},{"w":"kim","s":1.72},{"w":"tự","s":1.96},{"w":"tháp","s":2.18},{"w":"của","s":2.34},{"w":"mình","s":2.54},{"w":"và","s":2.74},{"w":"sẵn","s":3.16},{"w":"sàng","s":3.36},{"w":"bắt","s":3.62},{"w":"tay","s":3.84},{"w":"vào","s":3.98},{"w":"viết,","s":4.2},{"w":"bạn","s":4.7},{"w":"cần","s":4.8},{"w":"chắc","s":4.98},{"w":"chắn","s":5.18},{"w":"rằng","s":5.38},{"w":"mình","s":5.66},{"w":"sắp","s":5.9},{"w":"xếp","s":6.12},{"w":"các","s":6.32},{"w":"ý","s":6.54},{"w":"trên","s":6.66},{"w":"trang","s":6.96},{"w":"giấy","s":7.22},{"w":"theo","s":7.42},{"w":"cách","s":7.72},{"w":"làm","s":7.94},{"w":"nổi","s":8.26},{"w":"bật","s":8.44},{"w":"được","s":8.6},{"w":"những","s":8.84},{"w":"tầng","s":9.06},{"w":"tư","s":9.28},{"w":"duy","s":9.52},{"w":"khác","s":9.62},{"w":"nhau.","s":9.88},{"w":"Khi","s":10.62},{"w":"làm","s":10.66},{"w":"vậy,","s":10.84},{"w":"bạn","s":11.38},{"w":"sẽ","s":11.48},{"w":"tự","s":11.68},{"w":"nhiên","s":11.9},{"w":"phản","s":12.08},{"w":"ánh","s":12.38},{"w":"được","s":12.56},{"w":"cấu","s":12.78},{"w":"trúc","s":12.94},{"w":"phân","s":13.1},{"w":"tầng","s":13.32},{"w":"của","s":13.48},{"w":"kim","s":13.78},{"w":"tự","s":14.08},{"w":"tháp,","s":14.26},{"w":"như","s":14.46},{"w":"minh","s":14.88},{"w":"họa","s":15.1},{"w":"ở","s":15.34},{"w":"Sơ","s":15.6},{"w":"đồ","s":15.76},{"w":"23.","s":15.92},{"w":"Bạn","s":17.42},{"w":"có","s":17.5},{"w":"thể","s":17.7},{"w":"phản","s":17.84},{"w":"ánh","s":18.14},{"w":"cấu","s":18.32},{"w":"trúc","s":18.54},{"w":"phân","s":18.68},{"w":"tầng","s":18.9},{"w":"này","s":19.06},{"w":"bằng","s":19.3},{"w":"nhiều","s":19.56},{"w":"cách,","s":19.74},{"w":"phổ","s":20.28},{"w":"biến","s":20.42},{"w":"nhất","s":20.62},{"w":"là","s":20.82},{"w":"dùng","s":20.96},{"w":"tiêu","s":21.2},{"w":"đề","s":21.4},{"w":"(heading),","s":21.58},{"w":"gạch","s":22.3},{"w":"chân","s":22.46},{"w":"luận","s":22.62},{"w":"điểm,","s":22.78},{"w":"đánh","s":23.3},{"w":"số","s":23.42},{"w":"thập","s":23.6},{"w":"phân","s":23.82},{"w":"và","s":24},{"w":"trình","s":24.28},{"w":"bày","s":24.52},{"w":"thụt","s":24.7},{"w":"đầu","s":25.04},{"w":"dòng.","s":25.2},{"w":"Người","s":26.02},{"w":"ta","s":26.08},{"w":"tranh","s":26.26},{"w":"luận","s":26.46},{"w":"khá","s":26.6},{"w":"gay","s":26.88},{"w":"gắt","s":27.16},{"w":"xem","s":27.36},{"w":"cách","s":27.7},{"w":"trình","s":27.88},{"w":"bày","s":28.12},{"w":"nào","s":28.32},{"w":"mới","s":28.6},{"w":"là","s":28.76},{"w":"\"tốt","s":28.94},{"w":"nhất\".","s":29.1},{"w":"Bản","s":29.3},{"w":"thân","s":29.94},{"w":"tôi","s":30.04},{"w":"nghiêng","s":30.24},{"w":"về","s":30.44},{"w":"việc","s":30.62},{"w":"dùng","s":30.82},{"w":"tiêu","s":31.04},{"w":"đề","s":31.24},{"w":"như","s":31.4},{"w":"sẽ","s":31.62},{"w":"trình","s":31.86},{"w":"bày","s":32.12},{"w":"dưới","s":32.28},{"w":"đây.","s":32.5},{"w":"Tuy","s":33.22},{"w":"vậy,","s":33.36},{"w":"để","s":33.9},{"w":"tôn","s":34},{"w":"trọng","s":34.22},{"w":"những","s":34.42},{"w":"lý","s":34.58},{"w":"lẽ","s":34.8},{"w":"rất","s":35},{"w":"xác","s":35.28},{"w":"đáng","s":35.48},{"w":"của","s":35.72},{"w":"những","s":35.9},{"w":"người","s":36.08},{"w":"ủng","s":36.28},{"w":"hộ","s":36.54},{"w":"các","s":36.7},{"w":"cách","s":36.92},{"w":"còn","s":37.06},{"w":"lại,","s":37.26},{"w":"tôi","s":37.28},{"w":"cũng","s":37.8},{"w":"sẽ","s":37.94},{"w":"bàn","s":38.16},{"w":"về","s":38.38},{"w":"chúng.","s":38.6},{"w":"Dù","s":39.7},{"w":"bạn","s":39.88},{"w":"chọn","s":40.08},{"w":"cách","s":40.3},{"w":"trình","s":40.52},{"w":"bày","s":40.7},{"w":"nào,","s":40.84},{"w":"hãy","s":40.9},{"w":"nhớ","s":41.52},{"w":"rằng","s":41.78},{"w":"mục","s":42.02},{"w":"tiêu","s":42.24},{"w":"của","s":42.38},{"w":"bạn","s":42.58},{"w":"là","s":42.74},{"w":"giúp","s":42.92},{"w":"người","s":43.16},{"w":"đọc","s":43.38},{"w":"dễ","s":43.62},{"w":"hiểu","s":43.84},{"w":"hơn.","s":44.04},{"w":"Điều","s":44.86},{"w":"đó","s":44.98},{"w":"có","s":45.18},{"w":"nghĩa","s":45.36},{"w":"là","s":45.52},{"w":"cách","s":45.64},{"w":"trình","s":45.86},{"w":"bày","s":46.12},{"w":"phải","s":46.34},{"w":"được","s":46.56},{"w":"áp","s":46.74},{"w":"dụng","s":46.94},{"w":"đúng","s":47.1},{"w":"để","s":47.1},{"w":"phản","s":47.58},{"w":"ánh","s":47.86},{"w":"các","s":48.08},{"w":"mức","s":48.3},{"w":"trừu","s":48.5},{"w":"tượng","s":48.7},{"w":"(level","s":48.98},{"w":"of","s":49.42},{"w":"abstraction)","s":49.88},{"w":"trong","s":50.34},{"w":"lập","s":50.66},{"w":"luận","s":50.84},{"w":"của","s":50.96},{"w":"bạn.","s":51.14},{"w":"Tạo","s":51.84},{"w":"ra","s":52.04},{"w":"hình","s":52.18},{"w":"thức","s":52.36},{"w":"mong","s":52.52},{"w":"muốn","s":52.74},{"w":"mà","s":52.94},{"w":"thiếu","s":53.16},{"w":"phần","s":53.46},{"w":"nội","s":53.72},{"w":"dung","s":53.94},{"w":"tương","s":54.1},{"w":"xứng","s":54.38},{"w":"có","s":54.54},{"w":"thể","s":54.82},{"w":"gây","s":55},{"w":"rối","s":55.21},{"w":"loạn.","s":55.42},{"w":"Vì","s":56.12},{"w":"lẽ","s":56.24},{"w":"đó,","s":56.36},{"w":"bạn","s":56.94},{"w":"cần","s":57.04},{"w":"bảo","s":57.22},{"w":"đảm","s":57.42},{"w":"mình","s":57.66},{"w":"hiểu","s":57.8},{"w":"thật","s":58.06},{"w":"thấu","s":58.28},{"w":"đáo","s":58.56},{"w":"các","s":58.74},{"w":"quy","s":58.92},{"w":"tắc","s":59.08},{"w":"trước","s":59.26},{"w":"khi","s":59.44},{"w":"bắt","s":59.62},{"w":"tay","s":59.82},{"w":"áp","s":59.94},{"w":"dụng.","s":60.2},{"w":"Sơ","s":61.32},{"w":"đồ","s":61.52},{"w":"23","s":61.66},{"w":"—","s":61.89},{"w":"Tiêu","s":62.12},{"w":"đề","s":62.4},{"w":"phải","s":62.56},{"w":"phản","s":62.86},{"w":"ánh","s":63.2},{"w":"các","s":63.36},{"w":"tầng","s":63.62},{"w":"tư","s":63.82},{"w":"duy","s":64.04},{"w":"Tên","s":64.051},{"w":"sách","s":64.061},{"w":"hoặc","s":64.072},{"w":"Tiêu","s":64.082},{"w":"đề","s":64.093},{"w":"chương","s":64.103},{"w":"─────────►","s":64.114},{"w":"Tư","s":64.124},{"w":"duy","s":64.135},{"w":"lớn","s":64.145},{"w":"(cấp","s":64.156},{"w":"cao","s":64.166},{"w":"nhất)","s":64.177},{"w":"Tiêu","s":64.187},{"w":"đề","s":64.198},{"w":"mục","s":64.208},{"w":"(Section)","s":64.219},{"w":"Tiêu","s":64.229},{"w":"đề","s":64.24},{"w":"tiểu","s":64.25},{"w":"mục","s":64.261},{"w":"(Subsection)","s":64.271},{"w":"1.1.","s":64.282},{"w":"Đoạn","s":64.292},{"w":"văn","s":64.303},{"w":"được","s":64.313},{"w":"đánh","s":64.324},{"w":"số","s":64.334},{"w":"-","s":64.345},{"w":"Luận","s":64.355},{"w":"điểm","s":64.366},{"w":"gạch","s":64.376},{"w":"ngang","s":64.387},{"w":"(dash","s":64.397},{"w":"point)","s":64.408}]}