{"hash":"de8ba705393901d95d0b7cf3b801e2307838476632b082bccaec71e99173af00","n":2308,"dur":575.3639921920001,"words":[{"w":"Suy","s":0},{"w":"luận","s":0.16},{"w":"diễn","s":0.26},{"w":"dịch","s":0.48},{"w":"dường","s":0.64},{"w":"như","s":0.88},{"w":"là","s":1.08},{"w":"khuôn","s":1.24},{"w":"mẫu","s":1.38},{"w":"mà","s":1.62},{"w":"trí","s":1.86},{"w":"óc","s":2.08},{"w":"nói","s":2.3},{"w":"chung","s":2.6},{"w":"ưa","s":2.78},{"w":"dùng","s":3.04},{"w":"nhất","s":3.24},{"w":"trong","s":3.46},{"w":"phần","s":3.72},{"w":"lớn","s":3.94},{"w":"hoạt","s":4.14},{"w":"động","s":4.36},{"w":"tư","s":4.52},{"w":"duy,","s":4.76},{"w":"có","s":5.26},{"w":"lẽ","s":5.32},{"w":"vì","s":5.44},{"w":"nó","s":5.68},{"w":"dễ","s":5.88},{"w":"dựng","s":6.1},{"w":"hơn","s":6.38},{"w":"suy","s":6.56},{"w":"luận","s":6.78},{"w":"quy","s":6.9},{"w":"nạp.","s":7.1},{"w":"Dù","s":7.88},{"w":"sao","s":8},{"w":"đi","s":8.2},{"w":"nữa,","s":8.32},{"w":"nó","s":8.84},{"w":"thường","s":8.94},{"w":"là","s":9.16},{"w":"khuôn","s":9.3},{"w":"mẫu","s":9.48},{"w":"người","s":9.68},{"w":"ta","s":9.88},{"w":"theo","s":10.04},{"w":"khi","s":10.3},{"w":"giải","s":10.52},{"w":"quyết","s":10.8},{"w":"vấn","s":10.96},{"w":"đề,","s":11.16},{"w":"và","s":11.32},{"w":"do","s":11.7},{"w":"đó","s":11.88},{"w":"cũng","s":12.02},{"w":"là","s":12.2},{"w":"khuôn","s":12.34},{"w":"mẫu","s":12.54},{"w":"người","s":12.72},{"w":"ta","s":12.92},{"w":"hay","s":13.14},{"w":"cố","s":13.32},{"w":"theo","s":13.52},{"w":"khi","s":13.78},{"w":"truyền","s":14},{"w":"đạt","s":14.26},{"w":"suy","s":14.44},{"w":"nghĩ","s":14.64},{"w":"của","s":14.8},{"w":"mình.","s":15},{"w":"Nhưng","s":15.74},{"w":"tuy","s":15.86},{"w":"diễn","s":16.02},{"w":"dịch","s":16.22},{"w":"là","s":16.38},{"w":"cách","s":16.6},{"w":"tư","s":16.82},{"w":"duy","s":17.06},{"w":"hữu","s":17.18},{"w":"ích,","s":17.42},{"w":"nó","s":17.9},{"w":"lại","s":18.02},{"w":"là","s":18.18},{"w":"cách","s":18.36},{"w":"viết","s":18.54},{"w":"nặng","s":18.74},{"w":"nề","s":19},{"w":"—","s":19.1},{"w":"như","s":19.2},{"w":"tôi","s":19.4},{"w":"sẽ","s":19.56},{"w":"cố","s":19.8},{"w":"chỉ","s":20},{"w":"ra","s":20.2},{"w":"dưới","s":20.44},{"w":"đây.","s":20.6},{"w":"Cách","s":21.76},{"w":"thức","s":21.9},{"w":"hoạt","s":22.04},{"w":"động","s":22.26},{"w":"Trước","s":23.02},{"w":"hết,","s":23.18},{"w":"hãy","s":23.64},{"w":"hiểu","s":23.74},{"w":"suy","s":24.02},{"w":"luận","s":24.22},{"w":"diễn","s":24.32},{"w":"dịch","s":24.54},{"w":"là","s":24.66},{"w":"gì.","s":24.84},{"w":"Người","s":25},{"w":"ta","s":25.6},{"w":"thường","s":25.76},{"w":"mô","s":25.92},{"w":"tả","s":26.14},{"w":"nó","s":26.28},{"w":"dưới","s":26.5},{"w":"dạng","s":26.72},{"w":"một","s":26.98},{"w":"tam","s":27.24},{"w":"đoạn","s":27.44},{"w":"luận","s":27.58},{"w":"(syllogism","s":27.8},{"w":"—","s":28.16},{"w":"kiểu","s":28.52},{"w":"lập","s":29.04},{"w":"luận","s":29.24},{"w":"trong","s":29.28},{"w":"đó","s":29.8},{"w":"một","s":29.98},{"w":"kết","s":30.14},{"w":"luận","s":30.32},{"w":"được","s":30.42},{"w":"rút","s":30.64},{"w":"ra","s":30.78},{"w":"từ","s":30.98},{"w":"hai","s":31.2},{"w":"tiền","s":31.42},{"w":"đề,","s":31.64},{"w":"một","s":32.1},{"w":"đại","s":32.22},{"w":"và","s":32.4},{"w":"một","s":32.62},{"w":"tiểu).","s":32.78},{"w":"Tôi","s":33.44},{"w":"thấy","s":33.58},{"w":"những","s":33.78},{"w":"thuật","s":34},{"w":"ngữ","s":34.2},{"w":"ấy","s":34.34},{"w":"gây","s":34.62},{"w":"rối","s":34.85},{"w":"khi","s":35.08},{"w":"giải","s":35.32},{"w":"thích","s":35.6},{"w":"cách","s":35.76},{"w":"tư","s":35.98},{"w":"duy","s":36.2},{"w":"diễn","s":36.34},{"w":"dịch","s":36.64},{"w":"vận","s":36.78},{"w":"hành","s":37.04},{"w":"trong","s":37.24},{"w":"viết","s":37.52},{"w":"lách,","s":37.72},{"w":"nên","s":37.88},{"w":"tôi","s":38.28},{"w":"sẽ","s":38.48},{"w":"không","s":38.7},{"w":"dùng","s":38.88},{"w":"lại","s":39.1},{"w":"chúng","s":39.34},{"w":"nữa.","s":39.52},{"w":"Thay","s":40.64},{"w":"vào","s":40.78},{"w":"đó,","s":40.94},{"w":"hãy","s":41.4},{"w":"hình","s":41.5},{"w":"dung","s":41.72},{"w":"một","s":41.86},{"w":"lập","s":42.04},{"w":"luận","s":42.2},{"w":"diễn","s":42.38},{"w":"dịch","s":42.62},{"w":"là","s":42.74},{"w":"cái","s":43.12},{"w":"cần","s":43.38},{"w":"làm","s":43.58},{"w":"được","s":43.92},{"w":"ba","s":44.1},{"w":"việc:","s":44.24},{"w":"Đưa","s":45.44},{"w":"ra","s":45.58},{"w":"một","s":45.72},{"w":"phát","s":45.88},{"w":"biểu","s":46.08},{"w":"về","s":46.24},{"w":"một","s":46.46},{"w":"tình","s":46.66},{"w":"huống","s":46.86},{"w":"đang","s":47.02},{"w":"tồn","s":47.24},{"w":"tại","s":47.5},{"w":"trên","s":47.7},{"w":"thế","s":47.94},{"w":"giới.","s":48.12},{"w":"Đưa","s":49.3},{"w":"ra","s":49.44},{"w":"một","s":49.6},{"w":"phát","s":49.74},{"w":"biểu","s":49.92},{"w":"khác","s":50.06},{"w":"về","s":50.34},{"w":"một","s":50.5},{"w":"tình","s":50.66},{"w":"huống","s":50.86},{"w":"có","s":51},{"w":"liên","s":51.2},{"w":"quan,","s":51.4},{"w":"đang","s":52},{"w":"tồn","s":52.1},{"w":"tại","s":52.28},{"w":"trên","s":52.5},{"w":"thế","s":52.68},{"w":"giới","s":52.84},{"w":"vào","s":53.02},{"w":"cùng","s":53.3},{"w":"thời","s":53.48},{"w":"điểm.","s":53.72},{"w":"Phát","s":54.44},{"w":"biểu","s":54.58},{"w":"thứ","s":54.74},{"w":"hai","s":54.98},{"w":"liên","s":55.14},{"w":"hệ","s":55.36},{"w":"với","s":55.5},{"w":"phát","s":55.74},{"w":"biểu","s":55.96},{"w":"thứ","s":56.08},{"w":"nhất","s":56.32},{"w":"nếu","s":56.76},{"w":"nó","s":56.92},{"w":"bình","s":57.12},{"w":"luận","s":57.3},{"w":"về","s":57.46},{"w":"chủ","s":57.66},{"w":"ngữ","s":57.9},{"w":"hoặc","s":57.9},{"w":"về","s":58.38},{"w":"vị","s":58.64},{"w":"ngữ","s":58.74},{"w":"của","s":58.9},{"w":"phát","s":59.1},{"w":"biểu","s":59.26},{"w":"thứ","s":59.4},{"w":"nhất.","s":59.62},{"w":"Nêu","s":60.7},{"w":"ra","s":60.9},{"w":"hệ","s":61.08},{"w":"quả","s":61.28},{"w":"của","s":61.44},{"w":"việc","s":61.64},{"w":"hai","s":61.84},{"w":"tình","s":62.08},{"w":"huống","s":62.28},{"w":"này","s":62.42},{"w":"cùng","s":62.42},{"w":"tồn","s":62.94},{"w":"tại","s":63.18},{"w":"trên","s":63.36},{"w":"thế","s":63.54},{"w":"giới","s":63.7},{"w":"vào","s":63.7},{"w":"cùng","s":64.38},{"w":"một","s":64.56},{"w":"thời","s":64.8},{"w":"điểm.","s":65},{"w":"Sơ","s":66.14},{"w":"đồ","s":66.3},{"w":"18","s":66.46},{"w":"trình","s":66.8},{"w":"bày","s":67.16},{"w":"vài","s":67.34},{"w":"lập","s":67.66},{"w":"luận","s":67.78},{"w":"diễn","s":67.88},{"w":"dịch,","s":68.14},{"w":"mỗi","s":68.24},{"w":"lập","s":68.74},{"w":"luận","s":68.9},{"w":"đều","s":69.08},{"w":"có","s":69.36},{"w":"thể","s":69.54},{"w":"thấy","s":69.68},{"w":"rõ","s":69.88},{"w":"là","s":69.88},{"w":"làm","s":70.38},{"w":"đúng","s":70.64},{"w":"ba","s":70.84},{"w":"việc","s":71.06},{"w":"nói","s":71.3},{"w":"trên.","s":71.54},{"w":"Và","s":71.56},{"w":"trong","s":72.46},{"w":"từng","s":72.64},{"w":"trường","s":72.88},{"w":"hợp,","s":73.12},{"w":"luận","s":73.12},{"w":"điểm","s":73.72},{"w":"trên","s":73.88},{"w":"cùng","s":74.11},{"w":"phải","s":74.34},{"w":"tóm","s":74.62},{"w":"lược","s":74.84},{"w":"một","s":74.84},{"w":"cách","s":75.22},{"w":"đại","s":75.42},{"w":"khái","s":75.66},{"w":"các","s":75.86},{"w":"ý","s":76.12},{"w":"được","s":76.3},{"w":"gom","s":76.52},{"w":"bên","s":76.76},{"w":"dưới,","s":76.98},{"w":"dựa","s":77.04},{"w":"nặng","s":77.76},{"w":"vào","s":77.92},{"w":"luận","s":78.12},{"w":"điểm","s":78.22},{"w":"cuối.","s":78.4},{"w":"Như","s":79.16},{"w":"vậy,","s":79.36},{"w":"ta","s":79.8},{"w":"có","s":79.92},{"w":"\"Vì","s":80.1},{"w":"Socrates","s":80.38},{"w":"là","s":80.9},{"w":"người","s":81.2},{"w":"nên","s":81.2},{"w":"ông","s":81.7},{"w":"phải","s":81.88},{"w":"chết\",","s":82.12},{"w":"hay","s":82.38},{"w":"\"Vì","s":82.76},{"w":"các","s":82.98},{"w":"công","s":83.18},{"w":"đoàn","s":83.36},{"w":"hành","s":83.48},{"w":"xử","s":83.76},{"w":"như","s":83.94},{"w":"một","s":84.14},{"w":"thế","s":84.3},{"w":"lực","s":84.5},{"w":"độc","s":84.64},{"w":"quyền","s":84.94},{"w":"nên","s":85.14},{"w":"chúng","s":85.56},{"w":"phải","s":85.8},{"w":"chịu","s":86.04},{"w":"sự","s":86.26},{"w":"điều","s":86.42},{"w":"chỉnh","s":86.6},{"w":"của","s":86.78},{"w":"luật","s":86.96},{"w":"chống","s":87.06},{"w":"độc","s":87.34},{"w":"quyền\",","s":87.62},{"w":"hay","s":87.62},{"w":"\"Nếu","s":88.18},{"w":"muốn","s":88.32},{"w":"tăng","s":88.54},{"w":"sản","s":88.7},{"w":"lượng,","s":88.98},{"w":"bạn","s":89.44},{"w":"phải","s":89.54},{"w":"chỉnh","s":89.78},{"w":"sửa","s":90},{"w":"lại","s":90.22},{"w":"cấu","s":90.36},{"w":"trúc","s":90.52},{"w":"hiện","s":90.68},{"w":"thời","s":90.9},{"w":"của","s":91.04},{"w":"mình\",","s":91.26},{"w":"v.v.","s":91.76},{"w":"Sơ","s":93.08},{"w":"đồ","s":93.24},{"w":"18","s":93.4},{"w":"—","s":93.56},{"w":"Ví","s":93.72},{"w":"dụ","s":94.02},{"w":"về","s":94.16},{"w":"các","s":94.44},{"w":"lập","s":94.64},{"w":"luận","s":94.8},{"w":"diễn","s":94.96},{"w":"dịch","s":95.22},{"w":"Phát","s":96.02},{"w":"biểu","s":96.16},{"w":"1","s":96.32},{"w":"Phát","s":96.48},{"w":"biểu","s":96.72},{"w":"2","s":96.94},{"w":"Kết","s":97.16},{"w":"luận","s":97.36},{"w":"(\"vì","s":97.48},{"w":"vậy\")","s":97.78},{"w":"Con","s":99.2},{"w":"người","s":99.38},{"w":"ai","s":99.56},{"w":"cũng","s":99.8},{"w":"phải","s":100.04},{"w":"chết","s":100.24},{"w":"Socrates","s":100.5},{"w":"là","s":101},{"w":"người","s":101.32},{"w":"Vì","s":101.9},{"w":"vậy","s":102.04},{"w":"Socrates","s":102.3},{"w":"phải","s":102.82},{"w":"chết","s":103.14},{"w":"Mục","s":104},{"w":"đích","s":104.18},{"w":"của","s":104.28},{"w":"luật","s":104.5},{"w":"chống","s":104.62},{"w":"độc","s":104.88},{"w":"quyền","s":105.16},{"w":"là","s":105.34},{"w":"kích","s":105.7},{"w":"thích","s":105.94},{"w":"sản","s":106.08},{"w":"xuất","s":106.38},{"w":"và","s":106.54},{"w":"phân","s":106.78},{"w":"phối","s":107.02},{"w":"Thế","s":107.2},{"w":"độc","s":107.42},{"w":"quyền","s":107.7},{"w":"của","s":107.86},{"w":"công","s":108.04},{"w":"đoàn","s":108.26},{"w":"đối","s":108.44},{"w":"với","s":108.84},{"w":"nhân","s":109},{"w":"lực","s":109.18},{"w":"bóp","s":109.32},{"w":"nghẹt","s":109.56},{"w":"sản","s":109.78},{"w":"xuất","s":110.04},{"w":"và","s":110.22},{"w":"phân","s":110.44},{"w":"phối","s":110.68},{"w":"Vì","s":111.32},{"w":"vậy","s":111.36},{"w":"các","s":111.56},{"w":"công","s":111.78},{"w":"đoàn","s":111.96},{"w":"phải","s":112.14},{"w":"chịu","s":112.38},{"w":"sự","s":112.62},{"w":"điều","s":112.8},{"w":"chỉnh","s":112.98},{"w":"của","s":113.16},{"w":"luật","s":113.34},{"w":"chống","s":113.44},{"w":"độc","s":113.72},{"w":"quyền","s":113.98},{"w":"Bất","s":114.9},{"w":"kỳ","s":114.98},{"w":"công","s":115.12},{"w":"ty","s":115.34},{"w":"nào","s":115.44},{"w":"thỏa","s":115.72},{"w":"cả","s":116},{"w":"ba","s":116.22},{"w":"tiêu","s":116.4},{"w":"chí","s":116.66},{"w":"này","s":116.76},{"w":"đều","s":117.08},{"w":"đáng","s":117.38},{"w":"để","s":117.56},{"w":"mua","s":117.78},{"w":"lại","s":117.98},{"w":"Công","s":118.12},{"w":"ty","s":118.36},{"w":"A","s":118.52},{"w":"thỏa","s":118.68},{"w":"cả","s":118.98},{"w":"ba","s":119.2},{"w":"tiêu","s":119.34},{"w":"chí","s":119.56},{"w":"Vì","s":120.12},{"w":"vậy","s":120.24},{"w":"Công","s":120.42},{"w":"ty","s":120.58},{"w":"A","s":120.74},{"w":"đáng","s":120.94},{"w":"để","s":121.26},{"w":"mua","s":121.46},{"w":"lại","s":121.62},{"w":"Sản","s":122.5},{"w":"lượng","s":122.66},{"w":"tăng","s":122.8},{"w":"nhờ","s":123.04},{"w":"làm","s":123.3},{"w":"tốt","s":123.62},{"w":"bốn","s":123.82},{"w":"việc","s":124.08},{"w":"Cấu","s":124.28},{"w":"trúc","s":124.46},{"w":"hiện","s":124.6},{"w":"thời","s":124.92},{"w":"khiến","s":125.06},{"w":"bạn","s":125.54},{"w":"không","s":125.7},{"w":"thể","s":125.9},{"w":"làm","s":126.08},{"w":"tốt","s":126.3},{"w":"được","s":126.46},{"w":"việc","s":126.6},{"w":"nào","s":126.82},{"w":"trong","s":127.02},{"w":"số","s":127.28},{"w":"đó","s":127.46},{"w":"Vì","s":128},{"w":"vậy","s":128.06},{"w":"bạn","s":128.24},{"w":"cần","s":128.46},{"w":"chỉnh","s":128.66},{"w":"sửa","s":128.9},{"w":"lại","s":129.14},{"w":"cấu","s":129.28},{"w":"trúc","s":129.46},{"w":"hiện","s":129.62},{"w":"thời","s":129.86},{"w":"Công","s":130.76},{"w":"ty","s":130.88},{"w":"đã","s":131},{"w":"đạt","s":131.18},{"w":"được","s":131.44},{"w":"rất","s":131.64},{"w":"nhiều","s":131.84},{"w":"thành","s":132},{"w":"quả","s":132.26},{"w":"kể","s":132.46},{"w":"từ","s":132.74},{"w":"khi","s":132.86},{"w":"tập","s":133.08},{"w":"trung","s":133.3},{"w":"hóa","s":133.48},{"w":"hoạt","s":133.76},{"w":"động","s":133.96},{"w":"máy","s":134.14},{"w":"tính","s":134.36},{"w":"cách","s":134.56},{"w":"đây","s":134.78},{"w":"5","s":135.04},{"w":"năm","s":135.34},{"w":"Tuy","s":135.46},{"w":"nhiên,","s":135.66},{"w":"công","s":136.24},{"w":"ty","s":136.4},{"w":"đang","s":136.48},{"w":"bỏ","s":136.7},{"w":"lỡ","s":136.92},{"w":"một","s":137.14},{"w":"số","s":137.4},{"w":"cơ","s":137.52},{"w":"hội","s":137.74},{"w":"quan","s":137.86},{"w":"trọng","s":138.14},{"w":"để","s":138.34},{"w":"tận","s":138.48},{"w":"dụng","s":138.66},{"w":"năng","s":138.86},{"w":"lực","s":139.04},{"w":"máy","s":139.18},{"w":"tính","s":139.42},{"w":"của","s":139.56},{"w":"mình","s":139.74},{"w":"Theo","s":140.2},{"w":"đó,","s":140.3},{"w":"công","s":140.8},{"w":"ty","s":140.9},{"w":"nên","s":141.06},{"w":"tái","s":141.28},{"w":"định","s":141.6},{"w":"hướng","s":141.8},{"w":"cách","s":142.02},{"w":"tiếp","s":142.22},{"w":"cận","s":142.44},{"w":"tình","s":142.58},{"w":"hình","s":142.8},{"w":"hiện","s":142.92},{"w":"tại","s":143.14},{"w":"Đây","s":143.942},{"w":"là","s":144.062},{"w":"những","s":144.182},{"w":"ví","s":144.382},{"w":"dụ","s":144.602},{"w":"về","s":144.602},{"w":"lập","s":145.002},{"w":"luận","s":145.202},{"w":"diễn","s":145.342},{"w":"dịch","s":145.582},{"w":"trong","s":145.722},{"w":"đó","s":145.982},{"w":"từng","s":146.202},{"w":"bước","s":146.502},{"w":"suy","s":146.502},{"w":"luận","s":146.902},{"w":"đều","s":147.042},{"w":"được","s":147.502},{"w":"nêu","s":147.722},{"w":"ra","s":147.902},{"w":"đầy","s":148.162},{"w":"đủ.","s":148.402},{"w":"Nhưng","s":149.082},{"w":"đôi","s":149.182},{"w":"khi","s":149.342},{"w":"bạn","s":149.482},{"w":"sẽ","s":149.702},{"w":"muốn","s":149.922},{"w":"bỏ","s":150.122},{"w":"qua","s":150.302},{"w":"một","s":150.302},{"w":"bước","s":150.742},{"w":"và","s":150.922},{"w":"móc","s":151.302},{"w":"nối","s":151.502},{"w":"hai","s":151.722},{"w":"hay","s":151.982},{"w":"nhiều","s":152.202},{"w":"lập","s":152.362},{"w":"luận","s":152.542},{"w":"diễn","s":152.542},{"w":"dịch","s":152.982},{"w":"lại","s":153.122},{"w":"với","s":153.262},{"w":"nhau,","s":153.442},{"w":"bởi","s":153.642},{"w":"nếu","s":154.022},{"w":"đưa","s":154.182},{"w":"vào","s":154.322},{"w":"đủ","s":154.482},{"w":"mọi","s":154.482},{"w":"bước","s":154.922},{"w":"thì","s":155.102},{"w":"sẽ","s":155.422},{"w":"quá","s":155.662},{"w":"dài","s":155.882},{"w":"dòng","s":156.162},{"w":"và","s":156.162},{"w":"nghe","s":156.702},{"w":"ra","s":156.902},{"w":"mô","s":157.102},{"w":"phạm","s":157.302},{"w":"rườm","s":157.729},{"w":"rà.","s":158.155},{"w":"Việc","s":158.582},{"w":"móc","s":158.662},{"w":"nối","s":158.862},{"w":"các","s":159.042},{"w":"lập","s":159.242},{"w":"luận","s":159.422},{"w":"như","s":159.542},{"w":"vậy","s":159.742},{"w":"là","s":159.922},{"w":"hoàn","s":160.142},{"w":"toàn","s":160.442},{"w":"được","s":160.442},{"w":"phép,","s":160.822},{"w":"miễn","s":161.042},{"w":"là","s":161.422},{"w":"người","s":161.602},{"w":"đọc","s":161.782},{"w":"có","s":161.962},{"w":"khả","s":162.122},{"w":"năng","s":162.362},{"w":"nắm","s":162.362},{"w":"bắt","s":162.742},{"w":"và","s":162.882},{"w":"đồng","s":163.082},{"w":"tình","s":163.262},{"w":"với","s":163.462},{"w":"những","s":163.722},{"w":"bước","s":163.882},{"w":"bị","s":164.042},{"w":"lược","s":164.242},{"w":"bỏ.","s":164.362},{"w":"Sơ","s":165.142},{"w":"đồ","s":165.302},{"w":"19","s":165.462},{"w":"đưa","s":165.802},{"w":"ra","s":166.082},{"w":"một","s":166.242},{"w":"ví","s":166.382},{"w":"dụ","s":166.582},{"w":"về","s":166.722},{"w":"một","s":166.962},{"w":"lập","s":167.182},{"w":"luận","s":167.342},{"w":"diễn","s":167.522},{"w":"dịch","s":167.782},{"w":"được","s":167.942},{"w":"móc","s":168.182},{"w":"nối,","s":168.382},{"w":"có","s":168.522},{"w":"lẽ","s":168.982},{"w":"diễn","s":169.142},{"w":"ra","s":169.382},{"w":"đại","s":169.562},{"w":"khái","s":169.842},{"w":"như","s":170.082},{"w":"sau:","s":170.322},{"w":"Ta","s":171.502},{"w":"sản","s":171.622},{"w":"xuất","s":171.882},{"w":"đủ","s":172.062},{"w":"giấy","s":172.302},{"w":"báo","s":172.542},{"w":"cũ","s":172.722},{"w":"để","s":172.962},{"w":"đáp","s":173.402},{"w":"ứng","s":173.602},{"w":"nhu","s":173.762},{"w":"cầu","s":173.982},{"w":"của","s":174.142},{"w":"chính","s":174.342},{"w":"mình.","s":174.502},{"w":"Nhưng","s":175.622},{"w":"ta","s":175.762},{"w":"đã","s":175.942},{"w":"làm","s":176.082},{"w":"nhiều","s":176.322},{"w":"hơn","s":176.602},{"w":"mức","s":176.842},{"w":"đáp","s":177.042},{"w":"ứng","s":177.262},{"w":"nhu","s":177.422},{"w":"cầu","s":177.642},{"w":"của","s":177.822},{"w":"chính","s":178.002},{"w":"mình.","s":178.182},{"w":"Vì","s":179.322},{"w":"vậy","s":179.482},{"w":"ta","s":179.642},{"w":"đang","s":179.802},{"w":"thiếu","s":180.002},{"w":"hụt.","s":180.242},{"w":"Tình","s":181.402},{"w":"trạng","s":181.562},{"w":"thiếu","s":181.722},{"w":"hụt","s":181.882},{"w":"giấy","s":182.082},{"w":"báo","s":182.282},{"w":"cũ","s":182.522},{"w":"gây","s":182.782},{"w":"ra","s":183.062},{"w":"tình","s":183.262},{"w":"trạng","s":183.502},{"w":"thiếu","s":183.722},{"w":"hụt","s":183.922},{"w":"giấy","s":184.142},{"w":"in","s":184.402},{"w":"báo.","s":184.682},{"w":"Ta","s":185.822},{"w":"đang","s":185.922},{"w":"thiếu","s":186.102},{"w":"hụt","s":186.302},{"w":"giấy","s":186.522},{"w":"báo","s":186.722},{"w":"cũ.","s":186.942},{"w":"Vì","s":188.162},{"w":"vậy","s":188.302},{"w":"ta","s":188.482},{"w":"đang","s":188.642},{"w":"thiếu","s":188.802},{"w":"hụt","s":189.002},{"w":"giấy","s":189.222},{"w":"in","s":189.482},{"w":"báo.","s":189.762},{"w":"Sơ","s":190.922},{"w":"đồ","s":191.092},{"w":"19","s":191.262},{"w":"—","s":191.442},{"w":"Ví","s":191.622},{"w":"dụ","s":191.922},{"w":"về","s":192.062},{"w":"một","s":192.322},{"w":"lập","s":192.502},{"w":"luận","s":192.662},{"w":"diễn","s":192.842},{"w":"dịch","s":193.082},{"w":"được","s":193.262},{"w":"móc","s":193.522},{"w":"nối","s":193.722},{"w":"Luận","s":194.682},{"w":"điểm","s":194.802},{"w":"trên","s":194.982},{"w":"cùng:","s":195.202},{"w":"Việc","s":195.922},{"w":"tiếp","s":196.002},{"w":"tục","s":196.202},{"w":"bán","s":196.302},{"w":"giấy","s":196.582},{"w":"báo","s":196.822},{"w":"cũ","s":197.062},{"w":"cho","s":197.302},{"w":"các","s":197.522},{"w":"nước","s":197.722},{"w":"châu","s":197.882},{"w":"Á","s":198.062},{"w":"có","s":198.282},{"w":"thể","s":198.662},{"w":"làm","s":198.822},{"w":"trầm","s":199.082},{"w":"trọng","s":199.362},{"w":"thêm","s":199.562},{"w":"nguồn","s":199.802},{"w":"cung","s":200.082},{"w":"giấy","s":200.222},{"w":"in","s":200.502},{"w":"báo","s":200.762},{"w":"vốn","s":200.962},{"w":"đã","s":201.422},{"w":"khan","s":201.642},{"w":"hiếm","s":201.882},{"w":"ở","s":202.062},{"w":"Nam","s":202.282},{"w":"California.","s":202.502},{"w":"Nguồn","s":204.082},{"w":"cung","s":204.242},{"w":"giấy","s":204.382},{"w":"báo","s":204.562},{"w":"cũ","s":204.822},{"w":"ở","s":205.042},{"w":"Nam","s":205.342},{"w":"California","s":205.562},{"w":"vốn","s":206.162},{"w":"đủ","s":206.662},{"w":"để","s":206.822},{"w":"đáp","s":207.002},{"w":"ứng","s":207.182},{"w":"nhu","s":207.342},{"w":"cầu","s":207.542},{"w":"tại","s":207.722},{"w":"đây,","s":207.902},{"w":"ở","s":208.142},{"w":"hiện","s":208.502},{"w":"tại","s":208.662},{"w":"lẫn","s":208.842},{"w":"tương","s":209.042},{"w":"lai.","s":209.282},{"w":"Tuy","s":210.462},{"w":"nhiên,","s":210.522},{"w":"việc","s":211.022},{"w":"bán","s":211.142},{"w":"cho","s":211.402},{"w":"các","s":211.602},{"w":"nước","s":211.822},{"w":"châu","s":211.982},{"w":"Á","s":212.262},{"w":"đã","s":212.442},{"w":"gây","s":212.702},{"w":"ra","s":212.922},{"w":"một","s":213.202},{"w":"tình","s":213.382},{"w":"trạng","s":213.562},{"w":"thiếu","s":213.742},{"w":"hụt","s":213.962},{"w":"nghiêm","s":214.122},{"w":"trọng","s":214.362},{"w":"và","s":214.582},{"w":"sẽ","s":214.942},{"w":"còn","s":215.182},{"w":"dai","s":215.402},{"w":"dẳng.","s":216.112},{"w":"Tình","s":216.822},{"w":"trạng","s":216.942},{"w":"thiếu","s":217.102},{"w":"hụt","s":217.282},{"w":"nguyên","s":217.482},{"w":"liệu","s":217.662},{"w":"thô","s":217.802},{"w":"này","s":217.962},{"w":"sẽ","s":218.222},{"w":"làm","s":218.582},{"w":"trầm","s":218.862},{"w":"trọng","s":219.122},{"w":"thêm","s":219.362},{"w":"nguồn","s":219.582},{"w":"cung","s":219.822},{"w":"giấy","s":220.022},{"w":"in","s":220.282},{"w":"báo","s":220.562},{"w":"vốn","s":220.762},{"w":"đã","s":221.202},{"w":"khan","s":221.422},{"w":"hiếm","s":221.662},{"w":"ở","s":221.882},{"w":"Nam","s":222.082},{"w":"California.","s":222.262},{"w":"Bạn","s":222.842},{"w":"có","s":223.942},{"w":"thể","s":224.122},{"w":"thấy","s":224.262},{"w":"lập","s":224.462},{"w":"luận","s":224.682},{"w":"này","s":224.802},{"w":"sẽ","s":225.042},{"w":"chán","s":225.302},{"w":"đến","s":225.582},{"w":"thế","s":225.782},{"w":"nào","s":225.982},{"w":"khi","s":226.162},{"w":"đọc","s":226.542},{"w":"nếu","s":226.762},{"w":"ta","s":226.962},{"w":"đưa","s":227.122},{"w":"vào","s":227.322},{"w":"đủ","s":227.562},{"w":"từng","s":227.762},{"w":"bước;","s":228.022},{"w":"và","s":228.702},{"w":"nói","s":228.762},{"w":"chung","s":228.942},{"w":"đó","s":229.082},{"w":"chính","s":229.282},{"w":"là","s":229.482},{"w":"điều","s":229.622},{"w":"tôi","s":229.782},{"w":"phàn","s":230.042},{"w":"nàn","s":230.342},{"w":"nhất","s":230.502},{"w":"về","s":230.702},{"w":"việc","s":230.882},{"w":"dùng","s":231.102},{"w":"lập","s":231.322},{"w":"luận","s":231.562},{"w":"diễn","s":231.702},{"w":"dịch","s":231.942},{"w":"trong","s":232.082},{"w":"viết","s":232.342},{"w":"lách.","s":232.562},{"w":"Chúng","s":233.282},{"w":"nhàm","s":233.422},{"w":"chán,","s":233.722},{"w":"chủ","s":234.382},{"w":"yếu","s":234.422},{"w":"vì","s":234.622},{"w":"chúng","s":234.842},{"w":"biến","s":235.082},{"w":"một","s":235.302},{"w":"luận","s":235.482},{"w":"điểm","s":235.622},{"w":"lẽ","s":235.882},{"w":"ra","s":236.082},{"w":"phải","s":236.362},{"w":"thẳng","s":236.642},{"w":"tuột","s":236.862},{"w":"thành","s":237.022},{"w":"một","s":237.262},{"w":"câu","s":237.422},{"w":"chuyện","s":237.602},{"w":"trinh","s":237.782},{"w":"thám","s":238.022},{"w":"úp","s":238.202},{"w":"mở.","s":238.442},{"w":"Khi","s":239.522},{"w":"nào","s":239.682},{"w":"nên","s":239.882},{"w":"dùng","s":240.122},{"w":"Điều","s":241.082},{"w":"này","s":241.142},{"w":"dẫn","s":241.342},{"w":"tôi","s":241.502},{"w":"đến","s":241.722},{"w":"lời","s":241.882},{"w":"khuyên:","s":242.042},{"w":"ở","s":242.922},{"w":"cấp","s":242.962},{"w":"dòng","s":243.182},{"w":"chủ","s":243.382},{"w":"đề","s":243.642},{"w":"(key","s":243.942},{"w":"line),","s":244.242},{"w":"bạn","s":244.542},{"w":"hãy","s":244.662},{"w":"cố","s":244.782},{"w":"tránh","s":245.042},{"w":"dùng","s":245.322},{"w":"lập","s":245.542},{"w":"luận","s":245.742},{"w":"diễn","s":245.902},{"w":"dịch,","s":246.142},{"w":"mà","s":246.642},{"w":"thay","s":246.742},{"w":"vào","s":246.922},{"w":"đó","s":247.102},{"w":"luôn","s":247.282},{"w":"cố","s":247.502},{"w":"trình","s":247.762},{"w":"bày","s":247.962},{"w":"thông","s":248.142},{"w":"điệp","s":248.362},{"w":"của","s":248.482},{"w":"mình","s":248.662},{"w":"theo","s":248.842},{"w":"lối","s":249.042},{"w":"quy","s":249.182},{"w":"nạp.","s":249.362},{"w":"Vì","s":250.042},{"w":"sao?","s":250.242},{"w":"Vì","s":250.962},{"w":"như","s":251.062},{"w":"thế","s":251.262},{"w":"sẽ","s":251.462},{"w":"nhẹ","s":251.702},{"w":"nhàng","s":251.942},{"w":"hơn","s":252.182},{"w":"cho","s":252.442},{"w":"người","s":252.602},{"w":"đọc.","s":252.762},{"w":"Hãy","s":253.882},{"w":"xem","s":254.002},{"w":"bạn","s":254.242},{"w":"buộc","s":254.462},{"w":"người","s":254.662},{"w":"đọc","s":254.862},{"w":"phải","s":255.082},{"w":"làm","s":255.242},{"w":"gì","s":255.402},{"w":"khi","s":255.662},{"w":"yêu","s":255.962},{"w":"cầu","s":256.162},{"w":"họ","s":256.322},{"w":"tiếp","s":256.542},{"w":"nhận","s":256.782},{"w":"một","s":256.942},{"w":"bản","s":257.122},{"w":"báo","s":257.342},{"w":"cáo","s":257.562},{"w":"được","s":257.822},{"w":"tổ","s":258.162},{"w":"chức","s":258.342},{"w":"theo","s":258.482},{"w":"lối","s":258.702},{"w":"diễn","s":258.822},{"w":"dịch.","s":259.062},{"w":"Giả","s":259.742},{"w":"sử","s":259.962},{"w":"bạn","s":260.102},{"w":"muốn","s":260.302},{"w":"nói","s":260.482},{"w":"với","s":260.742},{"w":"họ","s":260.942},{"w":"rằng","s":261.102},{"w":"họ","s":261.362},{"w":"phải","s":261.642},{"w":"thay","s":261.862},{"w":"đổi","s":262.022},{"w":"theo","s":262.222},{"w":"một","s":262.462},{"w":"cách","s":262.622},{"w":"nào","s":262.762},{"w":"đó.","s":262.902},{"w":"Lập","s":263.542},{"w":"luận","s":263.702},{"w":"của","s":263.862},{"w":"bạn","s":264.042},{"w":"sẽ","s":264.222},{"w":"trông","s":264.422},{"w":"đại","s":264.682},{"w":"khái","s":264.922},{"w":"như","s":265.122},{"w":"thế","s":265.302},{"w":"này:","s":265.482},{"w":"Bạn","s":266.522},{"w":"phải","s":266.722},{"w":"thay","s":267.002},{"w":"đổi","s":267.202},{"w":"Vì","s":267.362},{"w":"sao?","s":268.182},{"w":"—","s":268.522},{"w":"Đây","s":268.862},{"w":"là","s":268.962},{"w":"những","s":269.082},{"w":"gì","s":269.302},{"w":"đang","s":269.482},{"w":"trục","s":269.722},{"w":"trặc:","s":269.962},{"w":"A1","s":270.202},{"w":"·","s":270.442},{"w":"B1","s":270.682},{"w":"·","s":270.922},{"w":"C1","s":271.162},{"w":"Vậy","s":271.402},{"w":"thì,","s":272.662},{"w":"—","s":272.752},{"w":"Đây","s":272.842},{"w":"là","s":273.182},{"w":"nguyên","s":273.302},{"w":"nhân","s":273.522},{"w":"của","s":273.662},{"w":"trục","s":273.822},{"w":"trặc:","s":274.088},{"w":"A2","s":274.353},{"w":"·","s":274.619},{"w":"B2","s":274.885},{"w":"·","s":275.151},{"w":"C2","s":275.416},{"w":"Đây","s":275.682},{"w":"là","s":276.822},{"w":"việc","s":276.942},{"w":"bạn","s":277.122},{"w":"nên","s":277.362},{"w":"làm:","s":277.502},{"w":"A3","s":277.832},{"w":"·","s":278.162},{"w":"B3","s":278.492},{"w":"·","s":278.822},{"w":"C3","s":279.152},{"w":"Để","s":279.482},{"w":"hấp","s":280.202},{"w":"thụ","s":280.382},{"w":"được","s":280.542},{"w":"mạch","s":280.742},{"w":"suy","s":280.962},{"w":"luận","s":281.202},{"w":"của","s":281.302},{"w":"bạn,","s":281.482},{"w":"trước","s":282.022},{"w":"hết","s":282.102},{"w":"người","s":282.322},{"w":"đọc","s":282.502},{"w":"phải","s":282.682},{"w":"tiếp","s":282.902},{"w":"nhận","s":283.142},{"w":"và","s":283.302},{"w":"ghi","s":283.502},{"w":"nhớ","s":283.682},{"w":"A–B–C","s":284.032},{"w":"của","s":284.382},{"w":"những","s":284.542},{"w":"gì","s":284.802},{"w":"đang","s":284.962},{"w":"trục","s":285.222},{"w":"trặc.","s":285.682},{"w":"Tôi","s":286.142},{"w":"đồng","s":286.222},{"w":"ý","s":286.402},{"w":"đây","s":286.562},{"w":"không","s":286.782},{"w":"phải","s":287.082},{"w":"việc","s":287.302},{"w":"khó;","s":287.504},{"w":"nhưng","s":288.304},{"w":"rồi","s":288.424},{"w":"bạn","s":288.624},{"w":"lại","s":288.824},{"w":"bắt","s":289.004},{"w":"họ","s":289.204},{"w":"lấy","s":289.404},{"w":"chữ","s":289.644},{"w":"A","s":289.824},{"w":"thứ","s":290.024},{"w":"nhất","s":290.284},{"w":"(cái","s":290.424},{"w":"đang","s":290.744},{"w":"trục","s":291.024},{"w":"trặc),","s":291.424},{"w":"mang","s":291.824},{"w":"nó","s":291.964},{"w":"sang","s":292.164},{"w":"và","s":292.484},{"w":"đối","s":292.724},{"w":"chiếu","s":292.844},{"w":"với","s":293.024},{"w":"chữ","s":293.204},{"w":"A","s":293.344},{"w":"thứ","s":293.604},{"w":"hai","s":293.924},{"w":"(cái","s":294.124},{"w":"gây","s":294.344},{"w":"ra","s":294.564},{"w":"trục","s":294.744},{"w":"trặc),","s":295.104},{"w":"rồi","s":295.464},{"w":"giữ","s":295.584},{"w":"điều","s":295.804},{"w":"đó","s":296.004},{"w":"trong","s":296.204},{"w":"đầu","s":296.404},{"w":"trong","s":296.584},{"w":"khi","s":296.824},{"w":"bạn","s":296.944},{"w":"làm","s":297.164},{"w":"đúng","s":297.384},{"w":"phép","s":297.564},{"w":"đối","s":297.804},{"w":"chiếu","s":297.984},{"w":"ấy","s":298.184},{"w":"cho","s":298.404},{"w":"các","s":298.624},{"w":"chữ","s":298.824},{"w":"B","s":298.984},{"w":"và","s":299.184},{"w":"C.","s":299.464},{"w":"Tiếp","s":300.224},{"w":"đó,","s":300.364},{"w":"bạn","s":300.544},{"w":"yêu","s":300.884},{"w":"cầu","s":301.064},{"w":"họ","s":301.244},{"w":"lặp","s":301.444},{"w":"lại","s":301.624},{"w":"quy","s":301.784},{"w":"trình,","s":302.004},{"w":"lần","s":302.004},{"w":"này","s":302.624},{"w":"nối","s":302.864},{"w":"chữ","s":303.104},{"w":"A","s":303.304},{"w":"thứ","s":303.524},{"w":"nhất","s":303.724},{"w":"(cái","s":303.924},{"w":"đang","s":304.204},{"w":"trục","s":304.484},{"w":"trặc)","s":304.684},{"w":"với","s":304.884},{"w":"chữ","s":305.064},{"w":"A","s":305.224},{"w":"thứ","s":305.484},{"w":"hai","s":305.824},{"w":"(cái","s":306.004},{"w":"gây","s":306.284},{"w":"ra","s":306.484},{"w":"trục","s":306.684},{"w":"trặc),","s":307.084},{"w":"rồi","s":307.484},{"w":"kéo","s":307.604},{"w":"cả","s":307.804},{"w":"mớ","s":308.024},{"w":"ấy","s":308.204},{"w":"đi","s":308.504},{"w":"để","s":308.644},{"w":"móc","s":308.904},{"w":"tiếp","s":309.084},{"w":"vào","s":309.304},{"w":"chữ","s":309.484},{"w":"A","s":309.664},{"w":"thứ","s":309.964},{"w":"ba","s":310.164},{"w":"(việc","s":310.344},{"w":"cần","s":310.604},{"w":"làm).","s":310.804},{"w":"Và","s":311.524},{"w":"y","s":311.604},{"w":"như","s":311.804},{"w":"vậy","s":312.004},{"w":"với","s":312.224},{"w":"các","s":312.384},{"w":"chữ","s":312.584},{"w":"B","s":312.764},{"w":"và","s":312.984},{"w":"C.","s":313.204},{"w":"Không","s":314.464},{"w":"những","s":314.584},{"w":"bạn","s":314.744},{"w":"bắt","s":314.964},{"w":"người","s":315.164},{"w":"đọc","s":315.384},{"w":"chờ","s":315.384},{"w":"rất","s":315.924},{"w":"lâu","s":316.124},{"w":"mới","s":316.344},{"w":"biết","s":316.544},{"w":"được","s":316.724},{"w":"sáng","s":316.924},{"w":"thứ","s":317.224},{"w":"Hai","s":317.444},{"w":"họ","s":317.444},{"w":"phải","s":318.004},{"w":"làm","s":318.184},{"w":"gì,","s":318.344},{"w":"bạn","s":318.844},{"w":"còn","s":318.924},{"w":"buộc","s":319.064},{"w":"họ","s":319.244},{"w":"diễn","s":319.424},{"w":"lại","s":319.604},{"w":"toàn","s":319.784},{"w":"bộ","s":320.104},{"w":"quá","s":320.244},{"w":"trình","s":320.504},{"w":"giải","s":320.664},{"w":"quyết","s":320.924},{"w":"vấn","s":321.044},{"w":"đề","s":321.244},{"w":"của","s":321.364},{"w":"bạn","s":321.524},{"w":"trước","s":321.524},{"w":"khi","s":321.884},{"w":"họ","s":322.044},{"w":"nhận","s":322.244},{"w":"được","s":322.384},{"w":"phần","s":322.564},{"w":"thưởng.","s":322.764},{"w":"Gần","s":323.524},{"w":"như","s":323.624},{"w":"thể","s":323.794},{"w":"bạn","s":323.964},{"w":"đang","s":324.164},{"w":"nói","s":324.364},{"w":"với","s":324.564},{"w":"họ:","s":324.744},{"w":"\"Tôi","s":324.764},{"w":"đã","s":325.464},{"w":"làm","s":325.584},{"w":"việc","s":325.804},{"w":"cực","s":326.004},{"w":"kỳ","s":326.224},{"w":"vất","s":326.364},{"w":"vả","s":326.564},{"w":"để","s":326.804},{"w":"có","s":327.184},{"w":"được","s":327.384},{"w":"câu","s":327.384},{"w":"trả","s":327.744},{"w":"lời","s":327.984},{"w":"này,","s":328.124},{"w":"và","s":328.364},{"w":"tôi","s":328.704},{"w":"sẽ","s":328.884},{"w":"bảo","s":329.044},{"w":"đảm","s":329.244},{"w":"rằng","s":329.244},{"w":"anh","s":329.764},{"w":"phải","s":330.044},{"w":"biết","s":330.244},{"w":"điều","s":330.444},{"w":"đó.\"","s":330.624},{"w":"Sẽ","s":331.364},{"w":"nhẹ","s":331.484},{"w":"nhàng","s":331.684},{"w":"hơn","s":331.924},{"w":"cho","s":332.184},{"w":"tất","s":332.364},{"w":"cả","s":332.564},{"w":"mọi","s":332.704},{"w":"người","s":332.884},{"w":"biết","s":333.044},{"w":"bao","s":333.224},{"w":"nếu","s":333.224},{"w":"bạn","s":333.864},{"w":"chỉ","s":334.064},{"w":"cần","s":334.264},{"w":"trình","s":334.544},{"w":"bày","s":334.784},{"w":"đúng","s":334.964},{"w":"thông","s":335.184},{"w":"điệp","s":335.404},{"w":"ấy","s":335.404},{"w":"theo","s":335.804},{"w":"lối","s":336.004},{"w":"quy","s":336.164},{"w":"nạp:","s":336.364},{"w":"Bạn","s":337.564},{"w":"phải","s":337.704},{"w":"thay","s":337.964},{"w":"đổi","s":338.184},{"w":"Như","s":338.984},{"w":"thế","s":339.084},{"w":"nào?","s":339.284},{"w":"—","s":339.579},{"w":"A2","s":339.875},{"w":"·","s":340.17},{"w":"A1","s":340.466},{"w":"·","s":340.761},{"w":"B2","s":341.056},{"w":"·","s":341.352},{"w":"B1","s":341.647},{"w":"·","s":341.942},{"w":"C2","s":342.238},{"w":"·","s":342.533},{"w":"C1","s":342.829},{"w":"Ở","s":343.124},{"w":"đây,","s":343.224},{"w":"thay","s":343.744},{"w":"vì","s":343.824},{"w":"trả","s":344.044},{"w":"lời","s":344.284},{"w":"câu","s":344.464},{"w":"hỏi","s":344.684},{"w":"\"Vì","s":344.844},{"w":"sao?\"","s":345.104},{"w":"trước","s":345.824},{"w":"rồi","s":346.004},{"w":"mới","s":346.244},{"w":"đến","s":346.444},{"w":"câu","s":346.624},{"w":"hỏi","s":346.844},{"w":"\"Như","s":347.044},{"w":"thế","s":347.224},{"w":"nào?\",","s":347.404},{"w":"bạn","s":348.104},{"w":"chỉ","s":348.224},{"w":"cần","s":348.424},{"w":"đảo","s":348.684},{"w":"lại","s":348.884},{"w":"trật","s":349.104},{"w":"tự.","s":349.304},{"w":"Và","s":350.024},{"w":"lúc","s":350.144},{"w":"này,","s":350.284},{"w":"dù","s":350.824},{"w":"ở","s":350.924},{"w":"các","s":351.124},{"w":"cấp","s":351.324},{"w":"thấp","s":351.464},{"w":"hơn","s":351.704},{"w":"bạn","s":351.984},{"w":"vẫn","s":352.264},{"w":"có","s":352.444},{"w":"thể","s":352.704},{"w":"có","s":352.884},{"w":"những","s":353.124},{"w":"lập","s":353.324},{"w":"luận","s":353.544},{"w":"diễn","s":353.664},{"w":"dịch,","s":353.924},{"w":"bạn","s":354.404},{"w":"vẫn","s":354.484},{"w":"đã","s":354.644},{"w":"trả","s":354.844},{"w":"lời","s":355.064},{"w":"thẳng","s":355.244},{"w":"vào","s":355.524},{"w":"câu","s":355.704},{"w":"hỏi","s":355.884},{"w":"chính","s":356.044},{"w":"yếu","s":356.324},{"w":"của","s":356.484},{"w":"người","s":356.664},{"w":"đọc,","s":356.844},{"w":"với","s":357.364},{"w":"những","s":357.484},{"w":"\"hàng","s":357.664},{"w":"rào\"","s":357.884},{"w":"rõ","s":358.084},{"w":"ràng","s":358.324},{"w":"trong","s":358.584},{"w":"tư","s":358.824},{"w":"duy","s":359.004},{"w":"phân","s":359.164},{"w":"tách","s":359.464},{"w":"các","s":359.604},{"w":"mảng","s":359.884},{"w":"chủ","s":360.104},{"w":"đề,","s":360.364},{"w":"và","s":360.364},{"w":"toàn","s":360.924},{"w":"bộ","s":361.164},{"w":"thông","s":361.284},{"w":"tin","s":361.524},{"w":"về","s":361.664},{"w":"mỗi","s":361.864},{"w":"chủ","s":362.024},{"w":"đề","s":362.264},{"w":"đều","s":362.484},{"w":"nằm","s":362.764},{"w":"gọn","s":362.944},{"w":"ở","s":363.124},{"w":"một","s":363.344},{"w":"chỗ.","s":363.544},{"w":"Nói","s":364.664},{"w":"theo","s":364.884},{"w":"một","s":365.004},{"w":"cách","s":365.144},{"w":"khác:","s":365.264},{"w":"ở","s":366.024},{"w":"cuối","s":366.144},{"w":"quá","s":366.284},{"w":"trình","s":366.504},{"w":"giải","s":366.704},{"w":"quyết","s":366.964},{"w":"vấn","s":367.104},{"w":"đề,","s":367.284},{"w":"bạn","s":367.484},{"w":"sẽ","s":367.864},{"w":"có","s":368.024},{"w":"một","s":368.204},{"w":"tập","s":368.364},{"w":"hợp","s":368.564},{"w":"các","s":368.704},{"w":"ý","s":368.964},{"w":"có","s":369.144},{"w":"thể","s":369.384},{"w":"được","s":369.564},{"w":"sắp","s":369.764},{"w":"xếp","s":369.964},{"w":"vào","s":370.144},{"w":"một","s":370.324},{"w":"Phiếu","s":370.544},{"w":"công","s":370.664},{"w":"tác","s":370.944},{"w":"Khuyến","s":371.104},{"w":"nghị","s":371.364},{"w":"(Recommendation","s":371.564},{"w":"Worksheet)","s":372.384},{"w":"như","s":373.204},{"w":"mô","s":373.624},{"w":"tả","s":373.844},{"w":"trong","s":374.004},{"w":"Sơ","s":374.364},{"w":"đồ","s":374.544},{"w":"20","s":374.724},{"w":".","s":375.284},{"w":"Phiếu","s":375.844},{"w":"này","s":375.884},{"w":"giúp","s":376.104},{"w":"bạn","s":376.344},{"w":"hình","s":376.624},{"w":"dung","s":376.804},{"w":"được","s":376.984},{"w":"rằng","s":377.204},{"w":"bạn","s":377.424},{"w":"đã","s":377.724},{"w":"thu","s":377.884},{"w":"thập","s":378.084},{"w":"các","s":378.264},{"w":"phát","s":378.484},{"w":"hiện","s":378.624},{"w":"dẫn","s":378.804},{"w":"bạn","s":378.984},{"w":"đến","s":379.184},{"w":"chỗ","s":379.404},{"w":"rút","s":379.624},{"w":"ra","s":379.864},{"w":"các","s":380.044},{"w":"kết","s":380.284},{"w":"luận,","s":380.424},{"w":"và","s":380.864},{"w":"từ","s":380.984},{"w":"các","s":381.144},{"w":"kết","s":381.324},{"w":"luận","s":381.444},{"w":"đó","s":381.524},{"w":"bạn","s":381.784},{"w":"xác","s":382.064},{"w":"định","s":382.284},{"w":"ra","s":382.444},{"w":"các","s":382.644},{"w":"khuyến","s":382.824},{"w":"nghị.","s":383.024},{"w":"Khi","s":384.204},{"w":"viết","s":384.344},{"w":"để","s":384.524},{"w":"khuyến","s":384.724},{"w":"nghị","s":384.964},{"w":"hành","s":385.104},{"w":"động,","s":385.344},{"w":"bạn","s":385.884},{"w":"sẽ","s":386.004},{"w":"không","s":386.204},{"w":"bao","s":386.344},{"w":"giờ","s":386.544},{"w":"nêu","s":386.744},{"w":"ra","s":387.024},{"w":"những","s":387.284},{"w":"phát","s":387.584},{"w":"hiện","s":387.844},{"w":"không","s":388.004},{"w":"dẫn","s":388.244},{"w":"tới","s":388.384},{"w":"kết","s":388.584},{"w":"luận","s":388.724},{"w":"nào,","s":388.824},{"w":"cũng","s":389.364},{"w":"không","s":389.464},{"w":"phát","s":389.644},{"w":"biểu","s":389.824},{"w":"những","s":389.984},{"w":"kết","s":390.184},{"w":"luận","s":390.364},{"w":"không","s":390.464},{"w":"dựa","s":390.724},{"w":"trên","s":390.924},{"w":"phát","s":391.064},{"w":"hiện","s":391.244},{"w":"nào.","s":391.384},{"w":"(Thật","s":392.204},{"w":"ra,","s":392.384},{"w":"kết","s":392.924},{"w":"luận","s":392.984},{"w":"chính","s":393.104},{"w":"là","s":393.384},{"w":"phát","s":393.604},{"w":"hiện","s":393.824},{"w":"ở","s":393.964},{"w":"một","s":394.164},{"w":"mức","s":394.364},{"w":"trừu","s":394.554},{"w":"tượng","s":394.744},{"w":"cao","s":394.924},{"w":"hơn.)","s":395.204},{"w":"Bạn","s":395.424},{"w":"cũng","s":395.884},{"w":"sẽ","s":396.044},{"w":"không","s":396.264},{"w":"có","s":396.464},{"w":"những","s":396.664},{"w":"kết","s":396.824},{"w":"luận","s":397.004},{"w":"không","s":397.104},{"w":"dẫn","s":397.344},{"w":"tới","s":397.544},{"w":"khuyến","s":397.744},{"w":"nghị","s":397.944},{"w":"nào,","s":398.084},{"w":"cũng","s":398.164},{"w":"không","s":398.704},{"w":"có","s":398.944},{"w":"những","s":399.124},{"w":"khuyến","s":399.284},{"w":"nghị","s":399.464},{"w":"không","s":399.644},{"w":"dựa","s":399.884},{"w":"trên","s":400.124},{"w":"kết","s":400.224},{"w":"luận","s":400.404},{"w":"nào.","s":400.504},{"w":"(Một","s":401.364},{"w":"kết","s":401.384},{"w":"luận","s":401.544},{"w":"có","s":401.664},{"w":"thể","s":401.884},{"w":"dẫn","s":402.024},{"w":"tới","s":402.224},{"w":"nhiều","s":402.504},{"w":"khuyến","s":402.784},{"w":"nghị,","s":403.024},{"w":"và","s":403.024},{"w":"nhiều","s":403.644},{"w":"kết","s":403.844},{"w":"luận","s":404.004},{"w":"có","s":404.124},{"w":"thể","s":404.364},{"w":"dẫn","s":404.504},{"w":"tới","s":404.704},{"w":"một","s":405.004},{"w":"khuyến","s":405.184},{"w":"nghị,","s":405.384},{"w":"nhưng","s":405.384},{"w":"giữa","s":406.024},{"w":"chúng","s":406.204},{"w":"bao","s":406.344},{"w":"giờ","s":406.584},{"w":"cũng","s":406.764},{"w":"phải","s":406.984},{"w":"có","s":407.144},{"w":"một","s":407.344},{"w":"mối","s":407.584},{"w":"liên","s":407.784},{"w":"hệ.)","s":408.004},{"w":"Các","s":408.884},{"w":"kết","s":408.944},{"w":"luận","s":409.064},{"w":"nhìn","s":409.164},{"w":"chung","s":409.424},{"w":"phát","s":409.604},{"w":"biểu","s":409.864},{"w":"chính","s":410.004},{"w":"cái","s":410.264},{"w":"vấn","s":410.444},{"w":"đề","s":410.604},{"w":"mà","s":410.744},{"w":"các","s":410.984},{"w":"khuyến","s":411.224},{"w":"nghị","s":411.424},{"w":"giải","s":411.584},{"w":"quyết.","s":411.904},{"w":"Do","s":412.684},{"w":"đó,","s":412.744},{"w":"tác","s":413.284},{"w":"dụng","s":413.364},{"w":"của","s":413.544},{"w":"khuyến","s":413.684},{"w":"nghị","s":413.884},{"w":"là","s":414.044},{"w":"giải","s":414.284},{"w":"quyết","s":414.584},{"w":"đúng","s":414.764},{"w":"cái","s":414.984},{"w":"vấn","s":415.144},{"w":"đề","s":415.304},{"w":"mà","s":415.304},{"w":"bạn","s":415.724},{"w":"đã","s":415.944},{"w":"kết","s":416.104},{"w":"luận","s":416.264},{"w":"là","s":416.404},{"w":"đang","s":416.684},{"w":"tồn","s":416.924},{"w":"tại.","s":417.204},{"w":"Chẳng","s":417.964},{"w":"hạn,","s":418.124},{"w":"doanh","s":418.624},{"w":"số","s":418.764},{"w":"giảm","s":418.944},{"w":"40%","s":419.284},{"w":"(phát","s":420.024},{"w":"hiện)","s":420.024},{"w":"là","s":420.784},{"w":"vì","s":420.964},{"w":"đối","s":421.124},{"w":"thủ","s":421.304},{"w":"cạnh","s":421.484},{"w":"tranh","s":421.744},{"w":"của","s":421.904},{"w":"ta","s":422.104},{"w":"đã","s":422.304},{"w":"bổ","s":422.664},{"w":"sung","s":422.884},{"w":"một","s":423.064},{"w":"tính","s":423.244},{"w":"năng","s":423.444},{"w":"mới","s":423.584},{"w":"vào","s":423.844},{"w":"sản","s":424.064},{"w":"phẩm","s":424.264},{"w":"của","s":424.424},{"w":"họ.","s":424.604},{"w":"Sơ","s":425.744},{"w":"đồ","s":425.884},{"w":"20","s":426.024},{"w":"PHÁT","s":427.144},{"w":"HIỆN","s":427.304},{"w":"KẾT","s":427.504},{"w":"LUẬN","s":427.724},{"w":"KHUYẾN","s":427.844},{"w":"NGHỊ","s":428.124},{"w":"Doanh","s":429.624},{"w":"số","s":429.764},{"w":"giảm","s":429.964},{"w":"40%.","s":430.284},{"w":"Đối","s":431.084},{"w":"thủ","s":431.704},{"w":"đã","s":431.844},{"w":"bổ","s":432.024},{"w":"sung","s":432.264},{"w":"tính","s":432.426},{"w":"năng","s":432.646},{"w":"mới.","s":432.786},{"w":"Không","s":433.546},{"w":"có","s":433.666},{"w":"gì","s":433.866},{"w":"khác","s":434.026},{"w":"thay","s":434.286},{"w":"đổi.","s":434.466},{"w":"Sự","s":435.246},{"w":"thay","s":435.326},{"w":"đổi","s":435.486},{"w":"từ","s":435.666},{"w":"phía","s":435.846},{"w":"cạnh","s":436.126},{"w":"tranh","s":436.386},{"w":"đã","s":436.586},{"w":"khiến","s":436.766},{"w":"ta","s":437.086},{"w":"mất","s":437.226},{"w":"40%","s":437.426},{"w":"doanh","s":438.346},{"w":"số.","s":438.566},{"w":"Thực","s":439.306},{"w":"hiện","s":439.386},{"w":"một","s":439.526},{"w":"thay","s":439.666},{"w":"đổi","s":439.806},{"w":"tương","s":439.986},{"w":"tự","s":440.246},{"w":"trên","s":440.386},{"w":"sản","s":440.566},{"w":"phẩm","s":440.786},{"w":"của","s":440.946},{"w":"ta.","s":441.166},{"w":"(kết","s":442.346},{"w":"luận","s":442.406},{"w":"về","s":442.526},{"w":"lý","s":442.706},{"w":"do","s":442.886},{"w":"doanh","s":443.086},{"w":"số","s":443.346},{"w":"sụt","s":443.606},{"w":"giảm),","s":443.846},{"w":"nên","s":444.186},{"w":"bạn","s":444.526},{"w":"khuyến","s":444.706},{"w":"nghị","s":444.966},{"w":"rằng","s":445.126},{"w":"ta","s":445.406},{"w":"nên","s":445.606},{"w":"bổ","s":445.766},{"w":"sung","s":446.006},{"w":"một","s":446.206},{"w":"tính","s":446.406},{"w":"năng","s":446.586},{"w":"tương","s":446.706},{"w":"tự","s":446.946},{"w":"vào","s":447.126},{"w":"sản","s":447.306},{"w":"phẩm","s":447.506},{"w":"của","s":447.666},{"w":"mình.","s":447.846},{"w":"Tác","s":448.606},{"w":"dụng","s":448.706},{"w":"của","s":448.826},{"w":"khuyến","s":448.966},{"w":"nghị","s":449.146},{"w":"là","s":449.326},{"w":"làm","s":449.686},{"w":"cho","s":449.946},{"w":"sản","s":450.106},{"w":"phẩm","s":450.306},{"w":"của","s":450.506},{"w":"ta","s":450.666},{"w":"có","s":450.846},{"w":"sức","s":451.106},{"w":"cạnh","s":451.306},{"w":"tranh","s":451.506},{"w":"trở","s":451.706},{"w":"lại.","s":451.946},{"w":"Giờ","s":453.066},{"w":"đây,","s":453.206},{"w":"bạn","s":453.726},{"w":"có","s":453.806},{"w":"thể","s":453.966},{"w":"trình","s":454.126},{"w":"bày","s":454.386},{"w":"thông","s":454.566},{"w":"điệp","s":454.806},{"w":"này","s":454.926},{"w":"theo","s":455.206},{"w":"lối","s":455.426},{"w":"diễn","s":455.586},{"w":"dịch,","s":455.806},{"w":"mỗi","s":456.366},{"w":"lần","s":456.386},{"w":"một","s":456.546},{"w":"cột,","s":456.766},{"w":"đại","s":457.286},{"w":"loại","s":457.366},{"w":"như","s":457.586},{"w":"sau:","s":457.846},{"w":"Doanh","s":458.986},{"w":"số","s":459.166},{"w":"giảm","s":459.366},{"w":"40%.","s":459.686},{"w":"Doanh","s":461.426},{"w":"số","s":461.646},{"w":"giảm","s":461.846},{"w":"là","s":462.246},{"w":"do","s":462.406},{"w":"những","s":462.606},{"w":"thay","s":462.806},{"w":"đổi","s":463.006},{"w":"từ","s":463.206},{"w":"phía","s":463.406},{"w":"cạnh","s":463.666},{"w":"tranh.","s":463.906},{"w":"Vì","s":465.106},{"w":"vậy,","s":465.286},{"w":"tôi","s":465.726},{"w":"khuyến","s":465.846},{"w":"nghị","s":466.046},{"w":"ta","s":466.206},{"w":"nên","s":466.426},{"w":"thực","s":466.586},{"w":"hiện","s":466.826},{"w":"những","s":466.946},{"w":"thay","s":467.146},{"w":"đổi","s":467.346},{"w":"tương","s":467.526},{"w":"tự.","s":467.806},{"w":"Hoặc","s":468.966},{"w":"bạn","s":469.106},{"w":"có","s":469.306},{"w":"thể","s":469.506},{"w":"đơn","s":469.666},{"w":"giản","s":469.886},{"w":"xoay","s":470.146},{"w":"toàn","s":470.406},{"w":"bộ","s":470.646},{"w":"sang","s":470.846},{"w":"trái","s":471.206},{"w":"90","s":471.406},{"w":"độ","s":471.786},{"w":"và","s":471.946},{"w":"bắt","s":472.366},{"w":"đầu","s":472.606},{"w":"ngay","s":472.786},{"w":"bằng","s":473.066},{"w":"khuyến","s":473.306},{"w":"nghị:","s":473.546},{"w":"Ta","s":474.666},{"w":"phải","s":474.826},{"w":"thiết","s":475.046},{"w":"kế","s":475.246},{"w":"lại","s":475.446},{"w":"sản","s":475.686},{"w":"phẩm","s":475.906},{"w":"để","s":476.126},{"w":"giành","s":476.346},{"w":"lại","s":476.566},{"w":"vị","s":476.786},{"w":"thế.","s":476.966},{"w":"Đối","s":478.066},{"w":"thủ","s":478.246},{"w":"cạnh","s":478.426},{"w":"tranh","s":478.686},{"w":"đã","s":478.866},{"w":"làm","s":479.026},{"w":"như","s":479.306},{"w":"vậy.","s":479.546},{"w":"Việc","s":480.686},{"w":"đó","s":480.826},{"w":"đã","s":480.986},{"w":"khiến","s":481.146},{"w":"ta","s":481.446},{"w":"mất","s":481.646},{"w":"40%","s":481.826},{"w":"thị","s":482.606},{"w":"phần.","s":482.886},{"w":"Vấn","s":484.066},{"w":"đề","s":484.266},{"w":"ở","s":484.386},{"w":"đây","s":484.586},{"w":"là:","s":484.746},{"w":"nên","s":485.506},{"w":"nói","s":485.626},{"w":"với","s":485.866},{"w":"người","s":486.086},{"w":"đọc","s":486.306},{"w":"vì","s":486.506},{"w":"sao","s":486.766},{"w":"họ","s":487.026},{"w":"phải","s":487.206},{"w":"thay","s":487.406},{"w":"đổi","s":487.606},{"w":"rồi","s":487.786},{"w":"mới","s":488.046},{"w":"đến","s":488.266},{"w":"cách","s":488.466},{"w":"thực","s":488.686},{"w":"hiện,","s":488.926},{"w":"hay","s":489.066},{"w":"nói","s":489.486},{"w":"rằng","s":489.726},{"w":"họ","s":489.926},{"w":"phải","s":490.146},{"w":"thay","s":490.346},{"w":"đổi","s":490.506},{"w":"và","s":490.706},{"w":"vì","s":490.986},{"w":"sao","s":491.286},{"w":"lại","s":491.486},{"w":"phải","s":491.646},{"w":"thế.","s":491.886},{"w":"Theo","s":492.606},{"w":"một","s":492.746},{"w":"nguyên","s":492.906},{"w":"tắc","s":493.126},{"w":"thực","s":493.286},{"w":"dụng,","s":493.546},{"w":"bao","s":493.626},{"w":"giờ","s":494.226},{"w":"cũng","s":494.406},{"w":"nên","s":494.606},{"w":"trình","s":494.786},{"w":"bày","s":495.046},{"w":"hành","s":495.186},{"w":"động","s":495.426},{"w":"trước","s":495.606},{"w":"khi","s":495.786},{"w":"trình","s":495.966},{"w":"bày","s":496.206},{"w":"lập","s":496.426},{"w":"luận,","s":496.686},{"w":"vì","s":496.806},{"w":"hành","s":497.266},{"w":"động","s":497.446},{"w":"mới","s":497.646},{"w":"là","s":497.906},{"w":"thứ","s":498.086},{"w":"người","s":498.246},{"w":"đọc","s":498.446},{"w":"quan","s":498.606},{"w":"tâm","s":498.846},{"w":"—","s":498.846},{"w":"trừ","s":498.846},{"w":"khi","s":499.306},{"w":"bạn","s":499.546},{"w":"rơi","s":499.766},{"w":"vào","s":499.986},{"w":"một","s":500.166},{"w":"trong","s":500.346},{"w":"những","s":500.506},{"w":"trường","s":500.666},{"w":"hợp","s":500.906},{"w":"hiếm","s":501.066},{"w":"hoi","s":501.306},{"w":"mà","s":501.306},{"w":"lập","s":501.886},{"w":"luận","s":502.066},{"w":"mới","s":502.186},{"w":"chính","s":502.486},{"w":"là","s":502.926},{"w":"thứ","s":503.066},{"w":"họ","s":503.286},{"w":"thật","s":503.506},{"w":"sự","s":503.766},{"w":"quan","s":503.946},{"w":"tâm.","s":504.206},{"w":"Tôi","s":504.906},{"w":"chỉ","s":505.046},{"w":"nghĩ","s":505.246},{"w":"ra","s":505.466},{"w":"được","s":505.666},{"w":"hai","s":505.906},{"w":"tình","s":506.086},{"w":"huống","s":506.286},{"w":"mà","s":506.486},{"w":"ở","s":506.726},{"w":"đó","s":506.906},{"w":"lập","s":507.066},{"w":"luận","s":507.266},{"w":"có","s":507.626},{"w":"thể","s":507.806},{"w":"quan","s":508.006},{"w":"trọng","s":508.286},{"w":"với","s":508.466},{"w":"người","s":508.646},{"w":"đọc","s":508.826},{"w":"hơn","s":509.086},{"w":"cả","s":509.326},{"w":"hành","s":509.506},{"w":"động:","s":509.666},{"w":"Nếu","s":510.846},{"w":"họ","s":510.946},{"w":"sẽ","s":511.086},{"w":"phản","s":511.306},{"w":"đối","s":511.606},{"w":"kết","s":511.746},{"w":"luận","s":511.926},{"w":"của","s":512.026},{"w":"bạn","s":512.186},{"w":"rất","s":512.426},{"w":"gay","s":512.646},{"w":"gắt,","s":512.866},{"w":"đến","s":513.386},{"w":"mức","s":513.526},{"w":"bạn","s":513.666},{"w":"phải","s":513.906},{"w":"chuẩn","s":514.106},{"w":"bị","s":514.266},{"w":"trước","s":514.426},{"w":"để","s":514.706},{"w":"họ","s":515.086},{"w":"chấp","s":515.326},{"w":"nhận","s":515.546},{"w":"nó.","s":515.686},{"w":"Nếu","s":516.866},{"w":"họ","s":516.966},{"w":"không","s":517.126},{"w":"thể","s":517.306},{"w":"hiểu","s":517.486},{"w":"nổi","s":517.726},{"w":"hành","s":517.946},{"w":"động","s":518.166},{"w":"nếu","s":518.346},{"w":"chưa","s":518.586},{"w":"được","s":518.766},{"w":"giải","s":518.926},{"w":"thích","s":519.186},{"w":"trước","s":519.326},{"w":"(như","s":519.326},{"w":"trong","s":520.026},{"w":"một","s":520.246},{"w":"bài","s":520.406},{"w":"viết","s":520.586},{"w":"về","s":520.806},{"w":"cách","s":521.246},{"w":"làm","s":521.446},{"w":"phân","s":521.706},{"w":"tích","s":521.906},{"w":"rủi","s":522.066},{"w":"ro),","s":522.366},{"w":"khiến","s":522.526},{"w":"bạn","s":522.966},{"w":"buộc","s":523.146},{"w":"phải","s":523.306},{"w":"đưa","s":523.526},{"w":"ra","s":523.666},{"w":"mạch","s":523.926},{"w":"lập","s":524.066},{"w":"luận","s":524.286},{"w":"làm","s":524.446},{"w":"nền","s":524.766},{"w":"cho","s":524.926},{"w":"nó.","s":525.166},{"w":"Tuy","s":526.366},{"w":"nhiên,","s":526.406},{"w":"rất","s":526.646},{"w":"ít","s":527.066},{"w":"người","s":527.226},{"w":"nhận","s":527.426},{"w":"tài","s":527.586},{"w":"liệu","s":527.766},{"w":"kinh","s":527.886},{"w":"doanh","s":528.086},{"w":"rơi","s":528.306},{"w":"vào","s":528.566},{"w":"hai","s":528.766},{"w":"nhóm","s":528.966},{"w":"trên,","s":529.166},{"w":"nên","s":529.806},{"w":"nhìn","s":529.886},{"w":"chung","s":530.086},{"w":"bạn","s":530.266},{"w":"sẽ","s":530.586},{"w":"thấy","s":530.786},{"w":"mình","s":530.966},{"w":"muốn","s":531.166},{"w":"cấu","s":531.406},{"w":"trúc","s":531.626},{"w":"dòng","s":531.786},{"w":"chủ","s":532.046},{"w":"đề","s":532.326},{"w":"của","s":532.486},{"w":"kim","s":532.726},{"w":"tự","s":533.006},{"w":"tháp","s":533.166},{"w":"thành","s":533.366},{"w":"một","s":533.786},{"w":"lập","s":533.966},{"w":"luận","s":534.146},{"w":"quy","s":534.286},{"w":"nạp.","s":534.486},{"w":"Lưu","s":535.626},{"w":"ý","s":535.786},{"w":"rằng","s":535.906},{"w":"ở","s":536.146},{"w":"đây","s":536.366},{"w":"tôi","s":536.546},{"w":"chỉ","s":536.806},{"w":"đang","s":537.026},{"w":"nói","s":537.266},{"w":"về","s":537.506},{"w":"dòng","s":537.726},{"w":"chủ","s":537.986},{"w":"đề,","s":538.246},{"w":"chứ","s":538.786},{"w":"không","s":538.806},{"w":"phải","s":538.986},{"w":"về","s":539.186},{"w":"các","s":539.426},{"w":"cấp","s":539.606},{"w":"thấp","s":539.746},{"w":"hơn.","s":539.926},{"w":"Lập","s":540.646},{"w":"luận","s":540.806},{"w":"diễn","s":540.926},{"w":"dịch","s":541.166},{"w":"rất","s":541.266},{"w":"dễ","s":541.506},{"w":"hấp","s":541.646},{"w":"thụ","s":541.846},{"w":"nếu","s":542.046},{"w":"chúng","s":542.506},{"w":"đến","s":542.726},{"w":"với","s":542.946},{"w":"người","s":543.166},{"w":"đọc","s":543.366},{"w":"một","s":543.626},{"w":"cách","s":543.846},{"w":"trực","s":543.966},{"w":"tiếp:","s":544.206},{"w":"Chim","s":545.306},{"w":"biết","s":545.506},{"w":"bay.","s":545.706},{"w":"Tôi","s":546.786},{"w":"là","s":546.946},{"w":"chim.","s":547.086},{"w":"Vì","s":548.366},{"w":"vậy,","s":548.606},{"w":"tôi","s":549.126},{"w":"biết","s":549.206},{"w":"bay.","s":549.366},{"w":"Nhưng","s":550.546},{"w":"khi","s":550.666},{"w":"bạn","s":550.846},{"w":"phải","s":551.066},{"w":"lội","s":551.266},{"w":"qua","s":551.486},{"w":"10","s":551.701},{"w":"hay","s":551.916},{"w":"12","s":552.131},{"w":"trang","s":552.346},{"w":"giấy","s":552.686},{"w":"giữa","s":552.966},{"w":"luận","s":553.186},{"w":"điểm","s":553.326},{"w":"thứ","s":553.486},{"w":"nhất","s":553.706},{"w":"và","s":553.846},{"w":"luận","s":554.066},{"w":"điểm","s":554.226},{"w":"thứ","s":554.386},{"w":"hai,","s":554.646},{"w":"rồi","s":554.846},{"w":"lại","s":555.266},{"w":"giữa","s":555.466},{"w":"luận","s":555.626},{"w":"điểm","s":555.766},{"w":"thứ","s":555.966},{"w":"hai","s":556.206},{"w":"và","s":556.406},{"w":"luận","s":556.606},{"w":"điểm","s":556.766},{"w":"thứ","s":556.926},{"w":"ba,","s":557.126},{"w":"thì","s":557.286},{"w":"chúng","s":557.686},{"w":"đánh","s":557.866},{"w":"mất","s":558.066},{"w":"sự","s":558.226},{"w":"sáng","s":558.446},{"w":"rõ","s":558.706},{"w":"tức","s":558.966},{"w":"thì","s":559.246},{"w":"ấy.","s":559.346},{"w":"Do","s":560.086},{"w":"đó,","s":560.226},{"w":"bạn","s":560.706},{"w":"nên","s":560.806},{"w":"đẩy","s":560.946},{"w":"suy","s":561.226},{"w":"luận","s":561.446},{"w":"diễn","s":561.566},{"w":"dịch","s":561.826},{"w":"xuống","s":561.926},{"w":"càng","s":562.246},{"w":"thấp","s":562.506},{"w":"trong","s":562.766},{"w":"kim","s":563.146},{"w":"tự","s":563.406},{"w":"tháp","s":563.606},{"w":"càng","s":563.766},{"w":"tốt,","s":564.026},{"w":"để","s":564.326},{"w":"giảm","s":564.706},{"w":"thiểu","s":564.986},{"w":"lượng","s":565.106},{"w":"thông","s":565.306},{"w":"tin","s":565.526},{"w":"chen","s":565.686},{"w":"vào","s":565.946},{"w":"giữa.","s":566.126},{"w":"Ở","s":566.906},{"w":"cấp","s":567.046},{"w":"đoạn","s":567.266},{"w":"văn,","s":567.446},{"w":"các","s":567.986},{"w":"lập","s":568.086},{"w":"luận","s":568.226},{"w":"diễn","s":568.386},{"w":"dịch","s":568.606},{"w":"rất","s":568.746},{"w":"tuyệt","s":568.946},{"w":"vời","s":569.166},{"w":"và","s":569.166},{"w":"tạo","s":569.746},{"w":"nên","s":569.986},{"w":"một","s":570.146},{"w":"mạch","s":570.346},{"w":"dễ","s":570.526},{"w":"theo","s":570.726},{"w":"dõi.","s":570.986},{"w":"Còn","s":571.746},{"w":"suy","s":571.906},{"w":"luận","s":572.086},{"w":"quy","s":572.206},{"w":"nạp","s":572.406},{"w":"thì","s":572.626},{"w":"bao","s":572.806},{"w":"giờ","s":573.026},{"w":"cũng","s":573.166},{"w":"dễ","s":573.366},{"w":"hấp","s":573.566},{"w":"thụ","s":573.766},{"w":"hơn","s":573.886},{"w":"ở","s":574.166},{"w":"các","s":574.386},{"w":"cấp","s":574.566},{"w":"cao.","s":574.646}]}